{
  "schemaVersion": 1,
  "generatedAt": "2026-06-06T10:34:06.393Z",
  "region": {
    "id": "south-aegean-kea",
    "name": "Kea"
  },
  "source": {
    "indexPath": "/data/geospatial/exposure/index.json"
  },
  "settings": {
    "maxFetchKm": 25,
    "stepKm": 0.5,
    "nearshoreLandGraceKm": 0.3,
    "nearshoreWaterSearchKm": 12,
    "nearshoreWaterSearchStepKm": 0.5,
    "fanAnglesDeg": [
      -30,
      -15,
      0,
      15,
      30
    ],
    "sectors": [
      "N",
      "NE",
      "E",
      "SE",
      "S",
      "SW",
      "W",
      "NW"
    ],
    "maskSource": "Natural Earth 1:10m land polygons",
    "maskConfidence": "medium"
  },
  "summary": {
    "beachCount": 34,
    "generatedProfiles": 34,
    "missingCoordinates": 0,
    "sectors": {
      "N": {
        "protected": 15,
        "partial": 13,
        "exposed": 6
      },
      "NE": {
        "protected": 15,
        "partial": 11,
        "exposed": 8
      },
      "E": {
        "protected": 16,
        "partial": 1,
        "exposed": 17
      },
      "SE": {
        "protected": 17,
        "partial": 1,
        "exposed": 16
      },
      "S": {
        "protected": 6,
        "partial": 17,
        "exposed": 11
      },
      "SW": {
        "protected": 17,
        "partial": 3,
        "exposed": 14
      },
      "W": {
        "protected": 18,
        "partial": 2,
        "exposed": 14
      },
      "NW": {
        "protected": 17,
        "partial": 0,
        "exposed": 17
      }
    }
  },
  "profiles": {
    "1804": {
      "beachId": 1804,
      "name": {
        "en": "Agios Filippos",
        "gr": "Άγιος Φίλιππος"
      },
      "coordinates": {
        "lat": 37.5787,
        "lon": 24.35857
      },
      "facingDeg": 131.6,
      "sectors": {
        "N": {
          "level": "protected",
          "fetchKm": 0.9,
          "blockedRayRatio": 1,
          "onshore": -0.664,
          "intensity": 10.1
        },
        "NE": {
          "level": "partial",
          "fetchKm": 15.6,
          "blockedRayRatio": 0.4,
          "onshore": 0.059,
          "intensity": 44.5
        },
        "E": {
          "level": "exposed",
          "fetchKm": 25,
          "blockedRayRatio": 0,
          "onshore": 0.748,
          "intensity": 87.4
        },
        "SE": {
          "level": "exposed",
          "fetchKm": 20.2,
          "blockedRayRatio": 0.4,
          "onshore": 0.998,
          "intensity": 83.9
        },
        "S": {
          "level": "exposed",
          "fetchKm": 20.2,
          "blockedRayRatio": 0.4,
          "onshore": 0.664,
          "intensity": 69.9
        },
        "SW": {
          "level": "partial",
          "fetchKm": 11.2,
          "blockedRayRatio": 0.6,
          "onshore": -0.059,
          "intensity": 35.2
        },
        "W": {
          "level": "protected",
          "fetchKm": 0.6,
          "blockedRayRatio": 1,
          "onshore": -0.748,
          "intensity": 7.6
        },
        "NW": {
          "level": "protected",
          "fetchKm": 0.3,
          "blockedRayRatio": 1,
          "onshore": -0.998,
          "intensity": 0.1
        }
      },
      "confidence": "medium"
    },
    "1805": {
      "beachId": 1805,
      "name": {
        "en": "Avythou",
        "gr": "Αβύθου"
      },
      "coordinates": {
        "lat": 37.54985,
        "lon": 24.27594
      },
      "facingDeg": 275,
      "sectors": {
        "N": {
          "level": "partial",
          "fetchKm": 14.4,
          "blockedRayRatio": 0.6,
          "onshore": 0.087,
          "intensity": 41.3
        },
        "NE": {
          "level": "protected",
          "fetchKm": 0,
          "blockedRayRatio": 1,
          "onshore": -0.643,
          "intensity": 10.7
        },
        "E": {
          "level": "protected",
          "fetchKm": 0,
          "blockedRayRatio": 1,
          "onshore": -0.996,
          "intensity": 0.1
        },
        "SE": {
          "level": "protected",
          "fetchKm": 0,
          "blockedRayRatio": 1,
          "onshore": -0.766,
          "intensity": 7
        },
        "S": {
          "level": "partial",
          "fetchKm": 10,
          "blockedRayRatio": 0.6,
          "onshore": -0.087,
          "intensity": 33.5
        },
        "SW": {
          "level": "exposed",
          "fetchKm": 25,
          "blockedRayRatio": 0,
          "onshore": 0.643,
          "intensity": 82.1
        },
        "W": {
          "level": "exposed",
          "fetchKm": 24.7,
          "blockedRayRatio": 0.2,
          "onshore": 0.996,
          "intensity": 91.8
        },
        "NW": {
          "level": "exposed",
          "fetchKm": 22.9,
          "blockedRayRatio": 0.6,
          "onshore": 0.766,
          "intensity": 67.1
        }
      },
      "confidence": "medium"
    },
    "1806": {
      "beachId": 1806,
      "name": {
        "en": "Vlanti",
        "gr": "Βλαντή"
      },
      "coordinates": {
        "lat": 37.55291,
        "lon": 24.32202
      },
      "facingDeg": 125,
      "sectors": {
        "N": {
          "level": "protected",
          "fetchKm": 0,
          "blockedRayRatio": 1,
          "onshore": -0.574,
          "intensity": 12.8
        },
        "NE": {
          "level": "partial",
          "fetchKm": 15,
          "blockedRayRatio": 0.4,
          "onshore": 0.174,
          "intensity": 49.3
        },
        "E": {
          "level": "exposed",
          "fetchKm": 25,
          "blockedRayRatio": 0,
          "onshore": 0.819,
          "intensity": 91
        },
        "SE": {
          "level": "exposed",
          "fetchKm": 17.7,
          "blockedRayRatio": 0.6,
          "onshore": 0.985,
          "intensity": 75.4
        },
        "S": {
          "level": "exposed",
          "fetchKm": 20.3,
          "blockedRayRatio": 0.4,
          "onshore": 0.574,
          "intensity": 66.1
        },
        "SW": {
          "level": "protected",
          "fetchKm": 10,
          "blockedRayRatio": 0.6,
          "onshore": -0.174,
          "intensity": 30.3
        },
        "W": {
          "level": "protected",
          "fetchKm": 0,
          "blockedRayRatio": 1,
          "onshore": -0.819,
          "intensity": 5.4
        },
        "NW": {
          "level": "protected",
          "fetchKm": 0,
          "blockedRayRatio": 1,
          "onshore": -0.985,
          "intensity": 0.5
        }
      },
      "confidence": "medium"
    },
    "1807": {
      "beachId": 1807,
      "name": {
        "en": "Vroskopos",
        "gr": "Βρόσκοπος"
      },
      "coordinates": {
        "lat": 37.60801,
        "lon": 24.27203
      },
      "facingDeg": 268.3,
      "sectors": {
        "N": {
          "level": "partial",
          "fetchKm": 20.2,
          "blockedRayRatio": 0.2,
          "onshore": -0.03,
          "intensity": 44.6
        },
        "NE": {
          "level": "protected",
          "fetchKm": 5.5,
          "blockedRayRatio": 0.8,
          "onshore": -0.728,
          "intensity": 8.7
        },
        "E": {
          "level": "protected",
          "fetchKm": 0.5,
          "blockedRayRatio": 1,
          "onshore": -1,
          "intensity": 0
        },
        "SE": {
          "level": "protected",
          "fetchKm": 0.9,
          "blockedRayRatio": 1,
          "onshore": -0.686,
          "intensity": 9.4
        },
        "S": {
          "level": "partial",
          "fetchKm": 15.6,
          "blockedRayRatio": 0.4,
          "onshore": 0.03,
          "intensity": 43.2
        },
        "SW": {
          "level": "exposed",
          "fetchKm": 25,
          "blockedRayRatio": 0,
          "onshore": 0.728,
          "intensity": 86.4
        },
        "W": {
          "level": "exposed",
          "fetchKm": 22.2,
          "blockedRayRatio": 0.4,
          "onshore": 1,
          "intensity": 84
        },
        "NW": {
          "level": "exposed",
          "fetchKm": 20.5,
          "blockedRayRatio": 0.6,
          "onshore": 0.686,
          "intensity": 64.1
        }
      },
      "confidence": "medium"
    },
    "1808": {
      "beachId": 1808,
      "name": {
        "en": "Gialiskari",
        "gr": "Γιαλισκάρι"
      },
      "coordinates": {
        "lat": 37.66238,
        "lon": 24.32129
      },
      "facingDeg": 317.3,
      "sectors": {
        "N": {
          "level": "exposed",
          "fetchKm": 10.6,
          "blockedRayRatio": 0.6,
          "onshore": 0.735,
          "intensity": 64.3
        },
        "NE": {
          "level": "protected",
          "fetchKm": 0.7,
          "blockedRayRatio": 1,
          "onshore": 0.04,
          "intensity": 31.2
        },
        "E": {
          "level": "protected",
          "fetchKm": 0.1,
          "blockedRayRatio": 1,
          "onshore": -0.678,
          "intensity": 9.7
        },
        "SE": {
          "level": "protected",
          "fetchKm": 0,
          "blockedRayRatio": 1,
          "onshore": -0.999,
          "intensity": 0
        },
        "S": {
          "level": "protected",
          "fetchKm": 0,
          "blockedRayRatio": 1,
          "onshore": -0.735,
          "intensity": 8
        },
        "SW": {
          "level": "protected",
          "fetchKm": 0.3,
          "blockedRayRatio": 1,
          "onshore": -0.04,
          "intensity": 28.8
        },
        "W": {
          "level": "partial",
          "fetchKm": 10.7,
          "blockedRayRatio": 1,
          "onshore": 0.678,
          "intensity": 50.3
        },
        "NW": {
          "level": "exposed",
          "fetchKm": 21.9,
          "blockedRayRatio": 0.4,
          "onshore": 0.999,
          "intensity": 84
        }
      },
      "confidence": "medium"
    },
    "1809": {
      "beachId": 1809,
      "name": {
        "en": "Kalamitsi",
        "gr": "Καλαμίτσι"
      },
      "coordinates": {
        "lat": 37.6228,
        "lon": 24.28074
      },
      "facingDeg": 270,
      "sectors": {
        "N": {
          "level": "partial",
          "fetchKm": 15,
          "blockedRayRatio": 0.4,
          "onshore": 0,
          "intensity": 42
        },
        "NE": {
          "level": "protected",
          "fetchKm": 0,
          "blockedRayRatio": 1,
          "onshore": -0.707,
          "intensity": 8.8
        },
        "E": {
          "level": "protected",
          "fetchKm": 0,
          "blockedRayRatio": 1,
          "onshore": -1,
          "intensity": 0
        },
        "SE": {
          "level": "protected",
          "fetchKm": 0,
          "blockedRayRatio": 1,
          "onshore": -0.707,
          "intensity": 8.8
        },
        "S": {
          "level": "partial",
          "fetchKm": 10.9,
          "blockedRayRatio": 0.6,
          "onshore": 0,
          "intensity": 37.3
        },
        "SW": {
          "level": "exposed",
          "fetchKm": 25,
          "blockedRayRatio": 0,
          "onshore": 0.707,
          "intensity": 85.4
        },
        "W": {
          "level": "exposed",
          "fetchKm": 21,
          "blockedRayRatio": 0.4,
          "onshore": 1,
          "intensity": 84
        },
        "NW": {
          "level": "exposed",
          "fetchKm": 19.2,
          "blockedRayRatio": 0.6,
          "onshore": 0.707,
          "intensity": 64.9
        }
      },
      "confidence": "medium"
    },
    "1810": {
      "beachId": 1810,
      "name": {
        "en": "Kalidonychi",
        "gr": "Καληδονύχι"
      },
      "coordinates": {
        "lat": 37.63747,
        "lon": 24.40113
      },
      "facingDeg": 99.8,
      "sectors": {
        "N": {
          "level": "protected",
          "fetchKm": 10.3,
          "blockedRayRatio": 0.6,
          "onshore": -0.17,
          "intensity": 30.6
        },
        "NE": {
          "level": "exposed",
          "fetchKm": 25,
          "blockedRayRatio": 0,
          "onshore": 0.576,
          "intensity": 78.8
        },
        "E": {
          "level": "exposed",
          "fetchKm": 25,
          "blockedRayRatio": 0,
          "onshore": 0.985,
          "intensity": 99.3
        },
        "SE": {
          "level": "exposed",
          "fetchKm": 24.9,
          "blockedRayRatio": 0.2,
          "onshore": 0.817,
          "intensity": 83.6
        },
        "S": {
          "level": "partial",
          "fetchKm": 18.9,
          "blockedRayRatio": 0.6,
          "onshore": 0.17,
          "intensity": 44.5
        },
        "SW": {
          "level": "protected",
          "fetchKm": 5.1,
          "blockedRayRatio": 0.8,
          "onshore": -0.576,
          "intensity": 13.4
        },
        "W": {
          "level": "protected",
          "fetchKm": 0,
          "blockedRayRatio": 1,
          "onshore": -0.985,
          "intensity": 0.4
        },
        "NW": {
          "level": "protected",
          "fetchKm": 0.1,
          "blockedRayRatio": 1,
          "onshore": -0.817,
          "intensity": 5.5
        }
      },
      "confidence": "medium"
    },
    "1811": {
      "beachId": 1811,
      "name": {
        "en": "Kaliskia",
        "gr": "Καλησκιά"
      },
      "coordinates": {
        "lat": 37.55556,
        "lon": 24.32563
      },
      "facingDeg": 125,
      "sectors": {
        "N": {
          "level": "protected",
          "fetchKm": 0,
          "blockedRayRatio": 1,
          "onshore": -0.574,
          "intensity": 12.8
        },
        "NE": {
          "level": "partial",
          "fetchKm": 15,
          "blockedRayRatio": 0.4,
          "onshore": 0.174,
          "intensity": 49.3
        },
        "E": {
          "level": "exposed",
          "fetchKm": 25,
          "blockedRayRatio": 0,
          "onshore": 0.819,
          "intensity": 91
        },
        "SE": {
          "level": "exposed",
          "fetchKm": 17.8,
          "blockedRayRatio": 0.6,
          "onshore": 0.985,
          "intensity": 75.4
        },
        "S": {
          "level": "exposed",
          "fetchKm": 20.4,
          "blockedRayRatio": 0.4,
          "onshore": 0.574,
          "intensity": 66.1
        },
        "SW": {
          "level": "protected",
          "fetchKm": 10,
          "blockedRayRatio": 0.6,
          "onshore": -0.174,
          "intensity": 30.3
        },
        "W": {
          "level": "protected",
          "fetchKm": 0,
          "blockedRayRatio": 1,
          "onshore": -0.819,
          "intensity": 5.4
        },
        "NW": {
          "level": "protected",
          "fetchKm": 0,
          "blockedRayRatio": 1,
          "onshore": -0.985,
          "intensity": 0.5
        }
      },
      "confidence": "medium"
    },
    "1812": {
      "beachId": 1812,
      "name": {
        "en": "Kalogiros",
        "gr": "Καλόγηρος"
      },
      "coordinates": {
        "lat": 37.61793,
        "lon": 24.2779
      },
      "facingDeg": 270,
      "sectors": {
        "N": {
          "level": "partial",
          "fetchKm": 15,
          "blockedRayRatio": 0.4,
          "onshore": 0,
          "intensity": 42
        },
        "NE": {
          "level": "protected",
          "fetchKm": 0,
          "blockedRayRatio": 1,
          "onshore": -0.707,
          "intensity": 8.8
        },
        "E": {
          "level": "protected",
          "fetchKm": 0,
          "blockedRayRatio": 1,
          "onshore": -1,
          "intensity": 0
        },
        "SE": {
          "level": "protected",
          "fetchKm": 0,
          "blockedRayRatio": 1,
          "onshore": -0.707,
          "intensity": 8.8
        },
        "S": {
          "level": "partial",
          "fetchKm": 10.9,
          "blockedRayRatio": 0.6,
          "onshore": 0,
          "intensity": 37.3
        },
        "SW": {
          "level": "exposed",
          "fetchKm": 25,
          "blockedRayRatio": 0,
          "onshore": 0.707,
          "intensity": 85.4
        },
        "W": {
          "level": "exposed",
          "fetchKm": 21,
          "blockedRayRatio": 0.4,
          "onshore": 1,
          "intensity": 84
        },
        "NW": {
          "level": "exposed",
          "fetchKm": 19.2,
          "blockedRayRatio": 0.6,
          "onshore": 0.707,
          "intensity": 64.9
        }
      },
      "confidence": "medium"
    },
    "1813": {
      "beachId": 1813,
      "name": {
        "en": "Kampi",
        "gr": "Καμπί"
      },
      "coordinates": {
        "lat": 37.56421,
        "lon": 24.27983
      },
      "facingDeg": 274.7,
      "sectors": {
        "N": {
          "level": "partial",
          "fetchKm": 14.4,
          "blockedRayRatio": 0.6,
          "onshore": 0.082,
          "intensity": 41.1
        },
        "NE": {
          "level": "protected",
          "fetchKm": 0,
          "blockedRayRatio": 1,
          "onshore": -0.647,
          "intensity": 10.6
        },
        "E": {
          "level": "protected",
          "fetchKm": 0,
          "blockedRayRatio": 1,
          "onshore": -0.997,
          "intensity": 0.1
        },
        "SE": {
          "level": "protected",
          "fetchKm": 0,
          "blockedRayRatio": 1,
          "onshore": -0.763,
          "intensity": 7.1
        },
        "S": {
          "level": "partial",
          "fetchKm": 10.1,
          "blockedRayRatio": 0.6,
          "onshore": -0.082,
          "intensity": 33.7
        },
        "SW": {
          "level": "exposed",
          "fetchKm": 25,
          "blockedRayRatio": 0,
          "onshore": 0.647,
          "intensity": 82.3
        },
        "W": {
          "level": "exposed",
          "fetchKm": 24.6,
          "blockedRayRatio": 0.2,
          "onshore": 0.997,
          "intensity": 91.8
        },
        "NW": {
          "level": "exposed",
          "fetchKm": 22.7,
          "blockedRayRatio": 0.6,
          "onshore": 0.763,
          "intensity": 67
        }
      },
      "confidence": "medium"
    },
    "1814": {
      "beachId": 1814,
      "name": {
        "en": "Kastriani",
        "gr": "Καστριανή"
      },
      "coordinates": {
        "lat": 37.66206,
        "lon": 24.39889
      },
      "facingDeg": 56.6,
      "sectors": {
        "N": {
          "level": "exposed",
          "fetchKm": 25,
          "blockedRayRatio": 0,
          "onshore": 0.55,
          "intensity": 77.5
        },
        "NE": {
          "level": "exposed",
          "fetchKm": 25,
          "blockedRayRatio": 0,
          "onshore": 0.98,
          "intensity": 99
        },
        "E": {
          "level": "exposed",
          "fetchKm": 24.7,
          "blockedRayRatio": 0.2,
          "onshore": 0.835,
          "intensity": 84.4
        },
        "SE": {
          "level": "partial",
          "fetchKm": 19.7,
          "blockedRayRatio": 0.4,
          "onshore": 0.201,
          "intensity": 50.4
        },
        "S": {
          "level": "protected",
          "fetchKm": 5,
          "blockedRayRatio": 0.8,
          "onshore": -0.55,
          "intensity": 14.2
        },
        "SW": {
          "level": "protected",
          "fetchKm": 0,
          "blockedRayRatio": 1,
          "onshore": -0.98,
          "intensity": 0.6
        },
        "W": {
          "level": "protected",
          "fetchKm": 0,
          "blockedRayRatio": 1,
          "onshore": -0.835,
          "intensity": 5
        },
        "NW": {
          "level": "protected",
          "fetchKm": 10.1,
          "blockedRayRatio": 0.6,
          "onshore": -0.201,
          "intensity": 29.3
        }
      },
      "confidence": "medium"
    },
    "1815": {
      "beachId": 1815,
      "name": {
        "en": "Koundouros",
        "gr": "Κούνδουρος"
      },
      "coordinates": {
        "lat": 37.58085,
        "lon": 24.27811
      },
      "facingDeg": 274.8,
      "sectors": {
        "N": {
          "level": "partial",
          "fetchKm": 15,
          "blockedRayRatio": 0.4,
          "onshore": 0.084,
          "intensity": 45.5
        },
        "NE": {
          "level": "protected",
          "fetchKm": 0,
          "blockedRayRatio": 1,
          "onshore": -0.645,
          "intensity": 10.6
        },
        "E": {
          "level": "protected",
          "fetchKm": 0,
          "blockedRayRatio": 1,
          "onshore": -0.996,
          "intensity": 0.1
        },
        "SE": {
          "level": "protected",
          "fetchKm": 0,
          "blockedRayRatio": 1,
          "onshore": -0.764,
          "intensity": 7.1
        },
        "S": {
          "level": "partial",
          "fetchKm": 10,
          "blockedRayRatio": 0.6,
          "onshore": -0.084,
          "intensity": 33.6
        },
        "SW": {
          "level": "exposed",
          "fetchKm": 25,
          "blockedRayRatio": 0,
          "onshore": 0.645,
          "intensity": 82.3
        },
        "W": {
          "level": "exposed",
          "fetchKm": 23.3,
          "blockedRayRatio": 0.2,
          "onshore": 0.996,
          "intensity": 91.8
        },
        "NW": {
          "level": "exposed",
          "fetchKm": 21.9,
          "blockedRayRatio": 0.4,
          "onshore": 0.764,
          "intensity": 74.1
        }
      },
      "confidence": "medium"
    },
    "1816": {
      "beachId": 1816,
      "name": {
        "en": "Ladou",
        "gr": "Λαδού"
      },
      "coordinates": {
        "lat": 37.68079,
        "lon": 24.35668
      },
      "facingDeg": 355.5,
      "sectors": {
        "N": {
          "level": "exposed",
          "fetchKm": 25,
          "blockedRayRatio": 0,
          "onshore": 0.997,
          "intensity": 99.8
        },
        "NE": {
          "level": "exposed",
          "fetchKm": 15,
          "blockedRayRatio": 0.4,
          "onshore": 0.649,
          "intensity": 69.3
        },
        "E": {
          "level": "protected",
          "fetchKm": 0,
          "blockedRayRatio": 1,
          "onshore": -0.078,
          "intensity": 27.6
        },
        "SE": {
          "level": "protected",
          "fetchKm": 0,
          "blockedRayRatio": 1,
          "onshore": -0.76,
          "intensity": 7.2
        },
        "S": {
          "level": "protected",
          "fetchKm": 0,
          "blockedRayRatio": 1,
          "onshore": -0.997,
          "intensity": 0.1
        },
        "SW": {
          "level": "protected",
          "fetchKm": 0,
          "blockedRayRatio": 1,
          "onshore": -0.649,
          "intensity": 10.5
        },
        "W": {
          "level": "partial",
          "fetchKm": 5.1,
          "blockedRayRatio": 0.8,
          "onshore": 0.078,
          "intensity": 34.2
        },
        "NW": {
          "level": "exposed",
          "fetchKm": 20.1,
          "blockedRayRatio": 0.2,
          "onshore": 0.76,
          "intensity": 81
        }
      },
      "confidence": "medium"
    },
    "1817": {
      "beachId": 1817,
      "name": {
        "en": "Liparo",
        "gr": "Λιπαρό"
      },
      "coordinates": {
        "lat": 37.55312,
        "lon": 24.27624
      },
      "facingDeg": 275,
      "sectors": {
        "N": {
          "level": "partial",
          "fetchKm": 14.4,
          "blockedRayRatio": 0.6,
          "onshore": 0.087,
          "intensity": 41.3
        },
        "NE": {
          "level": "protected",
          "fetchKm": 0,
          "blockedRayRatio": 1,
          "onshore": -0.643,
          "intensity": 10.7
        },
        "E": {
          "level": "protected",
          "fetchKm": 0,
          "blockedRayRatio": 1,
          "onshore": -0.996,
          "intensity": 0.1
        },
        "SE": {
          "level": "protected",
          "fetchKm": 0,
          "blockedRayRatio": 1,
          "onshore": -0.766,
          "intensity": 7
        },
        "S": {
          "level": "partial",
          "fetchKm": 10,
          "blockedRayRatio": 0.6,
          "onshore": -0.087,
          "intensity": 33.5
        },
        "SW": {
          "level": "exposed",
          "fetchKm": 25,
          "blockedRayRatio": 0,
          "onshore": 0.643,
          "intensity": 82.1
        },
        "W": {
          "level": "exposed",
          "fetchKm": 24.7,
          "blockedRayRatio": 0.2,
          "onshore": 0.996,
          "intensity": 91.8
        },
        "NW": {
          "level": "exposed",
          "fetchKm": 22.9,
          "blockedRayRatio": 0.6,
          "onshore": 0.766,
          "intensity": 67.1
        }
      },
      "confidence": "medium"
    },
    "1818": {
      "beachId": 1818,
      "name": {
        "en": "Lygia",
        "gr": "Λυγιά"
      },
      "coordinates": {
        "lat": 37.57202,
        "lon": 24.28104
      },
      "facingDeg": 274.8,
      "sectors": {
        "N": {
          "level": "partial",
          "fetchKm": 14.6,
          "blockedRayRatio": 0.6,
          "onshore": 0.084,
          "intensity": 41.2
        },
        "NE": {
          "level": "protected",
          "fetchKm": 0,
          "blockedRayRatio": 1,
          "onshore": -0.645,
          "intensity": 10.6
        },
        "E": {
          "level": "protected",
          "fetchKm": 0,
          "blockedRayRatio": 1,
          "onshore": -0.996,
          "intensity": 0.1
        },
        "SE": {
          "level": "protected",
          "fetchKm": 0,
          "blockedRayRatio": 1,
          "onshore": -0.764,
          "intensity": 7.1
        },
        "S": {
          "level": "partial",
          "fetchKm": 10,
          "blockedRayRatio": 0.6,
          "onshore": -0.084,
          "intensity": 33.6
        },
        "SW": {
          "level": "exposed",
          "fetchKm": 25,
          "blockedRayRatio": 0,
          "onshore": 0.645,
          "intensity": 82.3
        },
        "W": {
          "level": "exposed",
          "fetchKm": 23.4,
          "blockedRayRatio": 0.2,
          "onshore": 0.996,
          "intensity": 91.8
        },
        "NW": {
          "level": "exposed",
          "fetchKm": 21.7,
          "blockedRayRatio": 0.6,
          "onshore": 0.764,
          "intensity": 67
        }
      },
      "confidence": "medium"
    },
    "1819": {
      "beachId": 1819,
      "name": {
        "en": "Mavia",
        "gr": "Μαβιά"
      },
      "coordinates": {
        "lat": 37.55019,
        "lon": 24.32011
      },
      "facingDeg": 125,
      "sectors": {
        "N": {
          "level": "protected",
          "fetchKm": 0.1,
          "blockedRayRatio": 1,
          "onshore": -0.574,
          "intensity": 12.8
        },
        "NE": {
          "level": "partial",
          "fetchKm": 15.1,
          "blockedRayRatio": 0.4,
          "onshore": 0.174,
          "intensity": 49.3
        },
        "E": {
          "level": "exposed",
          "fetchKm": 25,
          "blockedRayRatio": 0,
          "onshore": 0.819,
          "intensity": 91
        },
        "SE": {
          "level": "exposed",
          "fetchKm": 17.8,
          "blockedRayRatio": 0.6,
          "onshore": 0.985,
          "intensity": 75.4
        },
        "S": {
          "level": "exposed",
          "fetchKm": 20.4,
          "blockedRayRatio": 0.4,
          "onshore": 0.574,
          "intensity": 66.1
        },
        "SW": {
          "level": "protected",
          "fetchKm": 10,
          "blockedRayRatio": 0.6,
          "onshore": -0.174,
          "intensity": 30.3
        },
        "W": {
          "level": "protected",
          "fetchKm": 0,
          "blockedRayRatio": 1,
          "onshore": -0.819,
          "intensity": 5.4
        },
        "NW": {
          "level": "protected",
          "fetchKm": 0,
          "blockedRayRatio": 1,
          "onshore": -0.985,
          "intensity": 0.5
        }
      },
      "confidence": "medium"
    },
    "1820": {
      "beachId": 1820,
      "name": {
        "en": "Mavrampeli",
        "gr": "Μαυραμπέλι"
      },
      "coordinates": {
        "lat": 37.62978,
        "lon": 24.28517
      },
      "facingDeg": 294.3,
      "sectors": {
        "N": {
          "level": "exposed",
          "fetchKm": 20,
          "blockedRayRatio": 0.2,
          "onshore": 0.412,
          "intensity": 64.9
        },
        "NE": {
          "level": "protected",
          "fetchKm": 5,
          "blockedRayRatio": 0.8,
          "onshore": -0.353,
          "intensity": 20.5
        },
        "E": {
          "level": "protected",
          "fetchKm": 0,
          "blockedRayRatio": 1,
          "onshore": -0.911,
          "intensity": 2.7
        },
        "SE": {
          "level": "protected",
          "fetchKm": 0,
          "blockedRayRatio": 1,
          "onshore": -0.935,
          "intensity": 1.9
        },
        "S": {
          "level": "protected",
          "fetchKm": 5,
          "blockedRayRatio": 0.8,
          "onshore": -0.412,
          "intensity": 18.6
        },
        "SW": {
          "level": "exposed",
          "fetchKm": 20,
          "blockedRayRatio": 0.2,
          "onshore": 0.353,
          "intensity": 62.3
        },
        "W": {
          "level": "exposed",
          "fetchKm": 21,
          "blockedRayRatio": 0.4,
          "onshore": 0.911,
          "intensity": 80.3
        },
        "NW": {
          "level": "exposed",
          "fetchKm": 19.2,
          "blockedRayRatio": 0.6,
          "onshore": 0.935,
          "intensity": 73.5
        }
      },
      "confidence": "medium"
    },
    "1821": {
      "beachId": 1821,
      "name": {
        "en": "Megales Poles",
        "gr": "Μεγάλες Πόλες"
      },
      "coordinates": {
        "lat": 37.5603,
        "lon": 24.33237
      },
      "facingDeg": 125.2,
      "sectors": {
        "N": {
          "level": "protected",
          "fetchKm": 0.1,
          "blockedRayRatio": 1,
          "onshore": -0.576,
          "intensity": 12.7
        },
        "NE": {
          "level": "partial",
          "fetchKm": 15.1,
          "blockedRayRatio": 0.4,
          "onshore": 0.17,
          "intensity": 49.1
        },
        "E": {
          "level": "exposed",
          "fetchKm": 25,
          "blockedRayRatio": 0,
          "onshore": 0.817,
          "intensity": 90.9
        },
        "SE": {
          "level": "exposed",
          "fetchKm": 17.7,
          "blockedRayRatio": 0.6,
          "onshore": 0.985,
          "intensity": 75.4
        },
        "S": {
          "level": "exposed",
          "fetchKm": 20.3,
          "blockedRayRatio": 0.4,
          "onshore": 0.576,
          "intensity": 66.2
        },
        "SW": {
          "level": "protected",
          "fetchKm": 10,
          "blockedRayRatio": 0.6,
          "onshore": -0.17,
          "intensity": 30.4
        },
        "W": {
          "level": "protected",
          "fetchKm": 0,
          "blockedRayRatio": 1,
          "onshore": -0.817,
          "intensity": 5.5
        },
        "NW": {
          "level": "protected",
          "fetchKm": 0,
          "blockedRayRatio": 1,
          "onshore": -0.985,
          "intensity": 0.4
        }
      },
      "confidence": "medium"
    },
    "1822": {
      "beachId": 1822,
      "name": {
        "en": "Mikres Poles",
        "gr": "Μικρές Πόλες"
      },
      "coordinates": {
        "lat": 37.55956,
        "lon": 24.32989
      },
      "facingDeg": 125,
      "sectors": {
        "N": {
          "level": "protected",
          "fetchKm": 0.1,
          "blockedRayRatio": 1,
          "onshore": -0.574,
          "intensity": 12.8
        },
        "NE": {
          "level": "partial",
          "fetchKm": 15.1,
          "blockedRayRatio": 0.4,
          "onshore": 0.174,
          "intensity": 49.3
        },
        "E": {
          "level": "exposed",
          "fetchKm": 25,
          "blockedRayRatio": 0,
          "onshore": 0.819,
          "intensity": 91
        },
        "SE": {
          "level": "exposed",
          "fetchKm": 17.7,
          "blockedRayRatio": 0.6,
          "onshore": 0.985,
          "intensity": 75.4
        },
        "S": {
          "level": "exposed",
          "fetchKm": 20.3,
          "blockedRayRatio": 0.4,
          "onshore": 0.574,
          "intensity": 66.1
        },
        "SW": {
          "level": "protected",
          "fetchKm": 10,
          "blockedRayRatio": 0.6,
          "onshore": -0.174,
          "intensity": 30.3
        },
        "W": {
          "level": "protected",
          "fetchKm": 0,
          "blockedRayRatio": 1,
          "onshore": -0.819,
          "intensity": 5.4
        },
        "NW": {
          "level": "protected",
          "fetchKm": 0,
          "blockedRayRatio": 1,
          "onshore": -0.985,
          "intensity": 0.5
        }
      },
      "confidence": "medium"
    },
    "1823": {
      "beachId": 1823,
      "name": {
        "en": "Xyla",
        "gr": "Ξύλα"
      },
      "coordinates": {
        "lat": 37.63929,
        "lon": 24.28991
      },
      "facingDeg": 294.3,
      "sectors": {
        "N": {
          "level": "exposed",
          "fetchKm": 20,
          "blockedRayRatio": 0.2,
          "onshore": 0.412,
          "intensity": 64.9
        },
        "NE": {
          "level": "protected",
          "fetchKm": 5,
          "blockedRayRatio": 0.8,
          "onshore": -0.353,
          "intensity": 20.5
        },
        "E": {
          "level": "protected",
          "fetchKm": 0,
          "blockedRayRatio": 1,
          "onshore": -0.911,
          "intensity": 2.7
        },
        "SE": {
          "level": "protected",
          "fetchKm": 0,
          "blockedRayRatio": 1,
          "onshore": -0.935,
          "intensity": 1.9
        },
        "S": {
          "level": "protected",
          "fetchKm": 5,
          "blockedRayRatio": 0.8,
          "onshore": -0.412,
          "intensity": 18.6
        },
        "SW": {
          "level": "exposed",
          "fetchKm": 20,
          "blockedRayRatio": 0.2,
          "onshore": 0.353,
          "intensity": 62.3
        },
        "W": {
          "level": "exposed",
          "fetchKm": 21,
          "blockedRayRatio": 0.4,
          "onshore": 0.911,
          "intensity": 80.3
        },
        "NW": {
          "level": "exposed",
          "fetchKm": 19.4,
          "blockedRayRatio": 0.6,
          "onshore": 0.935,
          "intensity": 73.5
        }
      },
      "confidence": "medium"
    },
    "1824": {
      "beachId": 1824,
      "name": {
        "en": "Orkos",
        "gr": "Ορκός"
      },
      "coordinates": {
        "lat": 37.60914,
        "lon": 24.38536
      },
      "facingDeg": 125,
      "sectors": {
        "N": {
          "level": "protected",
          "fetchKm": 5.1,
          "blockedRayRatio": 0.8,
          "onshore": -0.574,
          "intensity": 13.5
        },
        "NE": {
          "level": "partial",
          "fetchKm": 20.1,
          "blockedRayRatio": 0.2,
          "onshore": 0.174,
          "intensity": 54
        },
        "E": {
          "level": "exposed",
          "fetchKm": 25,
          "blockedRayRatio": 0,
          "onshore": 0.819,
          "intensity": 91
        },
        "SE": {
          "level": "exposed",
          "fetchKm": 22.9,
          "blockedRayRatio": 0.2,
          "onshore": 0.985,
          "intensity": 91.3
        },
        "S": {
          "level": "exposed",
          "fetchKm": 21.4,
          "blockedRayRatio": 0.4,
          "onshore": 0.574,
          "intensity": 66.1
        },
        "SW": {
          "level": "protected",
          "fetchKm": 10.3,
          "blockedRayRatio": 0.6,
          "onshore": -0.174,
          "intensity": 30.5
        },
        "W": {
          "level": "protected",
          "fetchKm": 0.1,
          "blockedRayRatio": 1,
          "onshore": -0.819,
          "intensity": 5.4
        },
        "NW": {
          "level": "protected",
          "fetchKm": 0,
          "blockedRayRatio": 1,
          "onshore": -0.985,
          "intensity": 0.5
        }
      },
      "confidence": "medium"
    },
    "1825": {
      "beachId": 1825,
      "name": {
        "en": "Otzias",
        "gr": "Οτζιάς"
      },
      "coordinates": {
        "lat": 37.67525,
        "lon": 24.35065
      },
      "facingDeg": 13.6,
      "sectors": {
        "N": {
          "level": "exposed",
          "fetchKm": 25,
          "blockedRayRatio": 0,
          "onshore": 0.972,
          "intensity": 98.6
        },
        "NE": {
          "level": "exposed",
          "fetchKm": 25,
          "blockedRayRatio": 0,
          "onshore": 0.854,
          "intensity": 92.7
        },
        "E": {
          "level": "partial",
          "fetchKm": 10.4,
          "blockedRayRatio": 0.6,
          "onshore": 0.235,
          "intensity": 45.6
        },
        "SE": {
          "level": "protected",
          "fetchKm": 0.5,
          "blockedRayRatio": 1,
          "onshore": -0.521,
          "intensity": 14.4
        },
        "S": {
          "level": "protected",
          "fetchKm": 0.1,
          "blockedRayRatio": 1,
          "onshore": -0.972,
          "intensity": 0.8
        },
        "SW": {
          "level": "protected",
          "fetchKm": 0,
          "blockedRayRatio": 1,
          "onshore": -0.854,
          "intensity": 4.4
        },
        "W": {
          "level": "protected",
          "fetchKm": 8.6,
          "blockedRayRatio": 0.8,
          "onshore": -0.235,
          "intensity": 25.1
        },
        "NW": {
          "level": "exposed",
          "fetchKm": 23.6,
          "blockedRayRatio": 0.2,
          "onshore": 0.521,
          "intensity": 70
        }
      },
      "confidence": "medium"
    },
    "1826": {
      "beachId": 1826,
      "name": {
        "en": "Petrousa",
        "gr": "Πετρούσα"
      },
      "coordinates": {
        "lat": 37.53984,
        "lon": 24.2763
      },
      "facingDeg": 270,
      "sectors": {
        "N": {
          "level": "partial",
          "fetchKm": 14.6,
          "blockedRayRatio": 0.6,
          "onshore": 0,
          "intensity": 38
        },
        "NE": {
          "level": "protected",
          "fetchKm": 0,
          "blockedRayRatio": 1,
          "onshore": -0.707,
          "intensity": 8.8
        },
        "E": {
          "level": "protected",
          "fetchKm": 0,
          "blockedRayRatio": 1,
          "onshore": -1,
          "intensity": 0
        },
        "SE": {
          "level": "protected",
          "fetchKm": 5,
          "blockedRayRatio": 0.8,
          "onshore": -0.707,
          "intensity": 9.3
        },
        "S": {
          "level": "partial",
          "fetchKm": 20,
          "blockedRayRatio": 0.2,
          "onshore": 0,
          "intensity": 46
        },
        "SW": {
          "level": "exposed",
          "fetchKm": 25,
          "blockedRayRatio": 0,
          "onshore": 0.707,
          "intensity": 85.4
        },
        "W": {
          "level": "exposed",
          "fetchKm": 25,
          "blockedRayRatio": 0,
          "onshore": 1,
          "intensity": 100
        },
        "NW": {
          "level": "exposed",
          "fetchKm": 23.6,
          "blockedRayRatio": 0.4,
          "onshore": 0.707,
          "intensity": 71.7
        }
      },
      "confidence": "medium"
    },
    "1827": {
      "beachId": 1827,
      "name": {
        "en": "Pisses",
        "gr": "Ποίσσες"
      },
      "coordinates": {
        "lat": 37.5998,
        "lon": 24.27665
      },
      "facingDeg": 268.3,
      "sectors": {
        "N": {
          "level": "partial",
          "fetchKm": 15.1,
          "blockedRayRatio": 0.4,
          "onshore": -0.03,
          "intensity": 40.8
        },
        "NE": {
          "level": "protected",
          "fetchKm": 0.1,
          "blockedRayRatio": 1,
          "onshore": -0.728,
          "intensity": 8.2
        },
        "E": {
          "level": "protected",
          "fetchKm": 0,
          "blockedRayRatio": 1,
          "onshore": -1,
          "intensity": 0
        },
        "SE": {
          "level": "protected",
          "fetchKm": 0.2,
          "blockedRayRatio": 1,
          "onshore": -0.686,
          "intensity": 9.4
        },
        "S": {
          "level": "partial",
          "fetchKm": 11,
          "blockedRayRatio": 0.6,
          "onshore": 0.03,
          "intensity": 38.4
        },
        "SW": {
          "level": "exposed",
          "fetchKm": 25,
          "blockedRayRatio": 0,
          "onshore": 0.728,
          "intensity": 86.4
        },
        "W": {
          "level": "exposed",
          "fetchKm": 23.1,
          "blockedRayRatio": 0.2,
          "onshore": 1,
          "intensity": 92
        },
        "NW": {
          "level": "exposed",
          "fetchKm": 21.6,
          "blockedRayRatio": 0.4,
          "onshore": 0.686,
          "intensity": 70.8
        }
      },
      "confidence": "medium"
    },
    "1828": {
      "beachId": 1828,
      "name": {
        "en": "Siderou",
        "gr": "Σιδερού"
      },
      "coordinates": {
        "lat": 37.65108,
        "lon": 24.40771
      },
      "facingDeg": 87.6,
      "sectors": {
        "N": {
          "level": "partial",
          "fetchKm": 25,
          "blockedRayRatio": 0,
          "onshore": 0.042,
          "intensity": 52.1
        },
        "NE": {
          "level": "exposed",
          "fetchKm": 25,
          "blockedRayRatio": 0,
          "onshore": 0.736,
          "intensity": 86.8
        },
        "E": {
          "level": "exposed",
          "fetchKm": 25,
          "blockedRayRatio": 0,
          "onshore": 0.999,
          "intensity": 100
        },
        "SE": {
          "level": "exposed",
          "fetchKm": 25,
          "blockedRayRatio": 0,
          "onshore": 0.677,
          "intensity": 83.8
        },
        "S": {
          "level": "partial",
          "fetchKm": 19.4,
          "blockedRayRatio": 0.4,
          "onshore": -0.042,
          "intensity": 40.2
        },
        "SW": {
          "level": "protected",
          "fetchKm": 5.6,
          "blockedRayRatio": 0.8,
          "onshore": -0.736,
          "intensity": 8.4
        },
        "W": {
          "level": "protected",
          "fetchKm": 0.5,
          "blockedRayRatio": 1,
          "onshore": -0.999,
          "intensity": 0
        },
        "NW": {
          "level": "protected",
          "fetchKm": 10.3,
          "blockedRayRatio": 0.6,
          "onshore": -0.677,
          "intensity": 11.9
        }
      },
      "confidence": "medium"
    },
    "1829": {
      "beachId": 1829,
      "name": {
        "en": "Spathi",
        "gr": "Σπαθί"
      },
      "coordinates": {
        "lat": 37.64638,
        "lon": 24.40123
      },
      "facingDeg": 100,
      "sectors": {
        "N": {
          "level": "protected",
          "fetchKm": 10,
          "blockedRayRatio": 0.6,
          "onshore": -0.174,
          "intensity": 30.3
        },
        "NE": {
          "level": "exposed",
          "fetchKm": 25,
          "blockedRayRatio": 0,
          "onshore": 0.574,
          "intensity": 78.7
        },
        "E": {
          "level": "exposed",
          "fetchKm": 25,
          "blockedRayRatio": 0,
          "onshore": 0.985,
          "intensity": 99.2
        },
        "SE": {
          "level": "exposed",
          "fetchKm": 25,
          "blockedRayRatio": 0,
          "onshore": 0.819,
          "intensity": 91
        },
        "S": {
          "level": "partial",
          "fetchKm": 14.2,
          "blockedRayRatio": 0.6,
          "onshore": 0.174,
          "intensity": 44.6
        },
        "SW": {
          "level": "protected",
          "fetchKm": 0.1,
          "blockedRayRatio": 1,
          "onshore": -0.574,
          "intensity": 12.8
        },
        "W": {
          "level": "protected",
          "fetchKm": 0,
          "blockedRayRatio": 1,
          "onshore": -0.985,
          "intensity": 0.5
        },
        "NW": {
          "level": "protected",
          "fetchKm": 0,
          "blockedRayRatio": 1,
          "onshore": -0.819,
          "intensity": 5.4
        }
      },
      "confidence": "medium"
    },
    "1830": {
      "beachId": 1830,
      "name": {
        "en": "Stefa",
        "gr": "Στέφα"
      },
      "coordinates": {
        "lat": 37.53803,
        "lon": 24.31013
      },
      "facingDeg": 125,
      "sectors": {
        "N": {
          "level": "protected",
          "fetchKm": 0,
          "blockedRayRatio": 1,
          "onshore": -0.574,
          "intensity": 12.8
        },
        "NE": {
          "level": "partial",
          "fetchKm": 15,
          "blockedRayRatio": 0.4,
          "onshore": 0.174,
          "intensity": 49.3
        },
        "E": {
          "level": "exposed",
          "fetchKm": 22.4,
          "blockedRayRatio": 0.2,
          "onshore": 0.819,
          "intensity": 83.7
        },
        "SE": {
          "level": "exposed",
          "fetchKm": 16.4,
          "blockedRayRatio": 0.8,
          "onshore": 0.985,
          "intensity": 67.5
        },
        "S": {
          "level": "exposed",
          "fetchKm": 21.7,
          "blockedRayRatio": 0.4,
          "onshore": 0.574,
          "intensity": 66.1
        },
        "SW": {
          "level": "protected",
          "fetchKm": 10,
          "blockedRayRatio": 0.6,
          "onshore": -0.174,
          "intensity": 30.3
        },
        "W": {
          "level": "protected",
          "fetchKm": 0,
          "blockedRayRatio": 1,
          "onshore": -0.819,
          "intensity": 5.4
        },
        "NW": {
          "level": "protected",
          "fetchKm": 0,
          "blockedRayRatio": 1,
          "onshore": -0.985,
          "intensity": 0.5
        }
      },
      "confidence": "medium"
    },
    "1831": {
      "beachId": 1831,
      "name": {
        "en": "Sykamia",
        "gr": "Συκαμιά"
      },
      "coordinates": {
        "lat": 37.62629,
        "lon": 24.39472
      },
      "facingDeg": 99.8,
      "sectors": {
        "N": {
          "level": "protected",
          "fetchKm": 10,
          "blockedRayRatio": 0.6,
          "onshore": -0.17,
          "intensity": 30.4
        },
        "NE": {
          "level": "exposed",
          "fetchKm": 25,
          "blockedRayRatio": 0,
          "onshore": 0.576,
          "intensity": 78.8
        },
        "E": {
          "level": "exposed",
          "fetchKm": 25,
          "blockedRayRatio": 0,
          "onshore": 0.985,
          "intensity": 99.3
        },
        "SE": {
          "level": "exposed",
          "fetchKm": 24.6,
          "blockedRayRatio": 0.2,
          "onshore": 0.817,
          "intensity": 83.6
        },
        "S": {
          "level": "partial",
          "fetchKm": 18.4,
          "blockedRayRatio": 0.6,
          "onshore": 0.17,
          "intensity": 44.5
        },
        "SW": {
          "level": "protected",
          "fetchKm": 5,
          "blockedRayRatio": 0.8,
          "onshore": -0.576,
          "intensity": 13.4
        },
        "W": {
          "level": "protected",
          "fetchKm": 0,
          "blockedRayRatio": 1,
          "onshore": -0.985,
          "intensity": 0.4
        },
        "NW": {
          "level": "protected",
          "fetchKm": 0,
          "blockedRayRatio": 1,
          "onshore": -0.817,
          "intensity": 5.5
        }
      },
      "confidence": "medium"
    },
    "1832": {
      "beachId": 1832,
      "name": {
        "en": "Schinos",
        "gr": "Σχίνος"
      },
      "coordinates": {
        "lat": 37.53162,
        "lon": 24.29989
      },
      "facingDeg": 140.2,
      "sectors": {
        "N": {
          "level": "protected",
          "fetchKm": 0,
          "blockedRayRatio": 1,
          "onshore": -0.768,
          "intensity": 7
        },
        "NE": {
          "level": "partial",
          "fetchKm": 10,
          "blockedRayRatio": 0.6,
          "onshore": -0.091,
          "intensity": 33.3
        },
        "E": {
          "level": "exposed",
          "fetchKm": 22.4,
          "blockedRayRatio": 0.2,
          "onshore": 0.64,
          "intensity": 75.4
        },
        "SE": {
          "level": "exposed",
          "fetchKm": 16.7,
          "blockedRayRatio": 0.8,
          "onshore": 0.996,
          "intensity": 67.9
        },
        "S": {
          "level": "exposed",
          "fetchKm": 22,
          "blockedRayRatio": 0.4,
          "onshore": 0.768,
          "intensity": 74.3
        },
        "SW": {
          "level": "partial",
          "fetchKm": 15,
          "blockedRayRatio": 0.4,
          "onshore": 0.091,
          "intensity": 45.8
        },
        "W": {
          "level": "protected",
          "fetchKm": 0,
          "blockedRayRatio": 1,
          "onshore": -0.64,
          "intensity": 10.8
        },
        "NW": {
          "level": "protected",
          "fetchKm": 0,
          "blockedRayRatio": 1,
          "onshore": -0.996,
          "intensity": 0.1
        }
      },
      "confidence": "medium"
    },
    "1833": {
      "beachId": 1833,
      "name": {
        "en": "Tilegrafos",
        "gr": "Τηλέγραφος"
      },
      "coordinates": {
        "lat": 37.5931,
        "lon": 24.37042
      },
      "facingDeg": 129,
      "sectors": {
        "N": {
          "level": "protected",
          "fetchKm": 0.3,
          "blockedRayRatio": 1,
          "onshore": -0.629,
          "intensity": 11.1
        },
        "NE": {
          "level": "partial",
          "fetchKm": 15.3,
          "blockedRayRatio": 0.4,
          "onshore": 0.105,
          "intensity": 46.4
        },
        "E": {
          "level": "exposed",
          "fetchKm": 25,
          "blockedRayRatio": 0,
          "onshore": 0.777,
          "intensity": 88.9
        },
        "SE": {
          "level": "exposed",
          "fetchKm": 22.8,
          "blockedRayRatio": 0.2,
          "onshore": 0.995,
          "intensity": 91.7
        },
        "S": {
          "level": "exposed",
          "fetchKm": 21.6,
          "blockedRayRatio": 0.4,
          "onshore": 0.629,
          "intensity": 68.4
        },
        "SW": {
          "level": "partial",
          "fetchKm": 10.8,
          "blockedRayRatio": 0.6,
          "onshore": -0.105,
          "intensity": 33.3
        },
        "W": {
          "level": "protected",
          "fetchKm": 0.1,
          "blockedRayRatio": 1,
          "onshore": -0.777,
          "intensity": 6.7
        },
        "NW": {
          "level": "protected",
          "fetchKm": 0,
          "blockedRayRatio": 1,
          "onshore": -0.995,
          "intensity": 0.2
        }
      },
      "confidence": "medium"
    },
    "1834": {
      "beachId": 1834,
      "name": {
        "en": "Freas",
        "gr": "Φρέας"
      },
      "coordinates": {
        "lat": 37.57941,
        "lon": 24.28003
      },
      "facingDeg": 274.7,
      "sectors": {
        "N": {
          "level": "partial",
          "fetchKm": 15,
          "blockedRayRatio": 0.4,
          "onshore": 0.082,
          "intensity": 45.4
        },
        "NE": {
          "level": "protected",
          "fetchKm": 0,
          "blockedRayRatio": 1,
          "onshore": -0.647,
          "intensity": 10.6
        },
        "E": {
          "level": "protected",
          "fetchKm": 0,
          "blockedRayRatio": 1,
          "onshore": -0.997,
          "intensity": 0.1
        },
        "SE": {
          "level": "protected",
          "fetchKm": 0,
          "blockedRayRatio": 1,
          "onshore": -0.763,
          "intensity": 7.1
        },
        "S": {
          "level": "partial",
          "fetchKm": 10.1,
          "blockedRayRatio": 0.6,
          "onshore": -0.082,
          "intensity": 33.7
        },
        "SW": {
          "level": "exposed",
          "fetchKm": 25,
          "blockedRayRatio": 0,
          "onshore": 0.647,
          "intensity": 82.3
        },
        "W": {
          "level": "exposed",
          "fetchKm": 23.4,
          "blockedRayRatio": 0.2,
          "onshore": 0.997,
          "intensity": 91.8
        },
        "NW": {
          "level": "exposed",
          "fetchKm": 22,
          "blockedRayRatio": 0.4,
          "onshore": 0.763,
          "intensity": 74
        }
      },
      "confidence": "medium"
    },
    "1835": {
      "beachId": 1835,
      "name": {
        "en": "Chyliamodou",
        "gr": "Χυλιαμόδου"
      },
      "coordinates": {
        "lat": 37.57733,
        "lon": 24.2809
      },
      "facingDeg": 274.5,
      "sectors": {
        "N": {
          "level": "partial",
          "fetchKm": 15,
          "blockedRayRatio": 0.4,
          "onshore": 0.078,
          "intensity": 45.3
        },
        "NE": {
          "level": "protected",
          "fetchKm": 0,
          "blockedRayRatio": 1,
          "onshore": -0.649,
          "intensity": 10.5
        },
        "E": {
          "level": "protected",
          "fetchKm": 0,
          "blockedRayRatio": 1,
          "onshore": -0.997,
          "intensity": 0.1
        },
        "SE": {
          "level": "protected",
          "fetchKm": 0,
          "blockedRayRatio": 1,
          "onshore": -0.76,
          "intensity": 7.2
        },
        "S": {
          "level": "partial",
          "fetchKm": 10.2,
          "blockedRayRatio": 0.6,
          "onshore": -0.078,
          "intensity": 33.9
        },
        "SW": {
          "level": "exposed",
          "fetchKm": 25,
          "blockedRayRatio": 0,
          "onshore": 0.649,
          "intensity": 82.5
        },
        "W": {
          "level": "exposed",
          "fetchKm": 23.4,
          "blockedRayRatio": 0.2,
          "onshore": 0.997,
          "intensity": 91.9
        },
        "NW": {
          "level": "exposed",
          "fetchKm": 22,
          "blockedRayRatio": 0.4,
          "onshore": 0.76,
          "intensity": 73.9
        }
      },
      "confidence": "medium"
    },
    "1836": {
      "beachId": 1836,
      "name": {
        "en": "Psathi",
        "gr": "Ψαθί"
      },
      "coordinates": {
        "lat": 37.61843,
        "lon": 24.39169
      },
      "facingDeg": 121.5,
      "sectors": {
        "N": {
          "level": "protected",
          "fetchKm": 5,
          "blockedRayRatio": 0.8,
          "onshore": -0.522,
          "intensity": 15.1
        },
        "NE": {
          "level": "partial",
          "fetchKm": 20,
          "blockedRayRatio": 0.2,
          "onshore": 0.233,
          "intensity": 56.7
        },
        "E": {
          "level": "exposed",
          "fetchKm": 25,
          "blockedRayRatio": 0,
          "onshore": 0.853,
          "intensity": 92.6
        },
        "SE": {
          "level": "exposed",
          "fetchKm": 23,
          "blockedRayRatio": 0.2,
          "onshore": 0.972,
          "intensity": 90.7
        },
        "S": {
          "level": "exposed",
          "fetchKm": 21.6,
          "blockedRayRatio": 0.4,
          "onshore": 0.522,
          "intensity": 63.9
        },
        "SW": {
          "level": "protected",
          "fetchKm": 10.1,
          "blockedRayRatio": 0.6,
          "onshore": -0.233,
          "intensity": 28.2
        },
        "W": {
          "level": "protected",
          "fetchKm": 0,
          "blockedRayRatio": 1,
          "onshore": -0.853,
          "intensity": 4.4
        },
        "NW": {
          "level": "protected",
          "fetchKm": 0,
          "blockedRayRatio": 1,
          "onshore": -0.972,
          "intensity": 0.8
        }
      },
      "confidence": "medium"
    },
    "1837": {
      "beachId": 1837,
      "name": {
        "en": "Psili Ammos",
        "gr": "Ψιλή Άμμος"
      },
      "coordinates": {
        "lat": 37.63653,
        "lon": 24.39885
      },
      "facingDeg": 100,
      "sectors": {
        "N": {
          "level": "protected",
          "fetchKm": 10,
          "blockedRayRatio": 0.6,
          "onshore": -0.174,
          "intensity": 30.3
        },
        "NE": {
          "level": "exposed",
          "fetchKm": 25,
          "blockedRayRatio": 0,
          "onshore": 0.574,
          "intensity": 78.7
        },
        "E": {
          "level": "exposed",
          "fetchKm": 25,
          "blockedRayRatio": 0,
          "onshore": 0.985,
          "intensity": 99.2
        },
        "SE": {
          "level": "exposed",
          "fetchKm": 24.8,
          "blockedRayRatio": 0.2,
          "onshore": 0.819,
          "intensity": 83.7
        },
        "S": {
          "level": "partial",
          "fetchKm": 13.7,
          "blockedRayRatio": 0.8,
          "onshore": 0.174,
          "intensity": 39.9
        },
        "SW": {
          "level": "protected",
          "fetchKm": 0,
          "blockedRayRatio": 1,
          "onshore": -0.574,
          "intensity": 12.8
        },
        "W": {
          "level": "protected",
          "fetchKm": 0,
          "blockedRayRatio": 1,
          "onshore": -0.985,
          "intensity": 0.5
        },
        "NW": {
          "level": "protected",
          "fetchKm": 0,
          "blockedRayRatio": 1,
          "onshore": -0.819,
          "intensity": 5.4
        }
      },
      "confidence": "medium"
    }
  }
}
